vrelease/__init__.py
vrelease/meta.py
vrelease/bin/vrelease-linux
vrelease/bin/vrelease-macos
vrelease/bin/vrelease-windows.exe
vrelease_bin-0.3.2.dist-info/LICENSE
vrelease_bin-0.3.2.dist-info/METADATA
vrelease_bin-0.3.2.dist-info/WHEEL
vrelease_bin-0.3.2.dist-info/entry_points.txt
vrelease_bin-0.3.2.dist-info/top_level.txt
vrelease_bin-0.3.2.dist-info/RECORD
