Metadata-Version: 2.1
Name: vrelease-bin
Version: 0.3.2
Summary: binary wrapper for vrelease - a kiss solution to easily create project releases
Home-page: https://github.com/vrelease/vrelease-py
Author: Caian R. Ertl
Author-email: hi@caian.org
License: CC0
Platform: UNKNOWN
Classifier: Environment :: Console
Classifier: Programming Language :: Python
Classifier: Programming Language :: Python :: 3.6
Classifier: Programming Language :: Python :: 3.7
Classifier: Programming Language :: Python :: 3.8
Classifier: Programming Language :: Python :: 3.9
Classifier: License :: CC0 1.0 Universal (CC0 1.0) Public Domain Dedication
Requires-Python: >=3.5
License-File: LICENSE
